rubric/__init__.py
rubric/constants.py
rubric/core/__init__.py
rubric/core/base.py
rubric/core/checklist.py
rubric/core/node.py
rubric/core/scorer.py
rubric/core/tree.py
rubric/generate/__init__.py
rubric/generate/tree_generator.py
rubric/prompts/generate-rubric-checklist-fast-system.jinja
rubric/prompts/generate-rubric-checklist-fast-user.jinja
rubric/prompts/generate-rubric-tree-system.jinja
rubric/prompts/generate-rubric-tree-user.jinja
rubric/prompts/generate-scorer-function-system.jinja
rubric/prompts/generate-scorer-function-user.jinja
rubric/utils/__init__.py
rubric/utils/llm_client.py
rubric/utils/llm_tools.py
rubric/utils/prompt_retriever.py
rubric/utils/visualizer.py
ai_rubric-0.2.2.dist-info/METADATA
ai_rubric-0.2.2.dist-info/WHEEL
ai_rubric-0.2.2.dist-info/licenses/LICENSE
ai_rubric-0.2.2.dist-info/RECORD
