Metadata-Version: 2.4
Name: ai-rubric
Version: 0.2.2
Summary: Structured verification with LLMs.
Project-URL: Repository, https://github.com/ApGa/rubric
Author-email: Apurva Gandhi <apurvasgandhi@gmail.com>
License-Expression: MIT
License-File: LICENSE
Requires-Python: >=3.11
Requires-Dist: jinja2>=3.1.0
Requires-Dist: litellm>=1.75.0
Requires-Dist: networkx>=3.5.0
Requires-Dist: plotly>=5.0.0
Provides-Extra: dev
Requires-Dist: mypy; extra == 'dev'
Requires-Dist: pre-commit; extra == 'dev'
Requires-Dist: pytest; extra == 'dev'
Requires-Dist: ruff; extra == 'dev'
